<?xml version="1.0" encoding="UTF-8"?>
<map>
  <element name="background_5element_1" type="0" x="0" y="0" isFlipped="false" isFlippedVer="false" width="360" height="456"/>
  <element name="background_5element_2" type="0" x="48" y="72" isFlipped="false" isFlippedVer="false" width="24" height="24"/>
  <element name="background_5element_2" type="0" x="72" y="72" isFlipped="false" isFlippedVer="false" width="24" height="24"/>
  <element name="background_5element_2" type="0" x="96" y="72" isFlipped="false" isFlippedVer="false" width="24" height="24"/>
  <element name="background_5element_2" type="0" x="120" y="72" isFlipped="false" isFlippedVer="false" width="24" height="24"/>
  <element name="background_5element_2" type="0" x="144" y="72" isFlipped="false" isFlippedVer="false" width="24" height="24"/>
  <element name="background_5element_2" type="0" x="168" y="72" isFlipped="false" isFlippedVer="false" width="24" height="24"/>
  <element name="background_5element_2" type="0" x="192" y="72" isFlipped="false" isFlippedVer="false" width="24" height="24"/>
  <element name="background_5element_2" type="0" x="216" y="72" isFlipped="false" isFlippedVer="false" width="24" height="24"/>
  <element name="background_5element_2" type="0" x="240" y="72" isFlipped="false" isFlippedVer="false" width="24" height="24"/>
  <element name="background_5element_2" type="0" x="264" y="72" isFlipped="false" isFlippedVer="false" width="24" height="24"/>
  <element name="background_5element_2" type="0" x="288" y="72" isFlipped="false" isFlippedVer="false" width="24" height="24"/>
  <element name="background_5element_2" type="0" x="48" y="360" isFlipped="false" isFlippedVer="false" width="24" height="24"/>
  <element name="background_5element_2" type="0" x="72" y="360" isFlipped="false" isFlippedVer="false" width="24" height="24"/>
  <element name="background_5element_2" type="0" x="96" y="360" isFlipped="false" isFlippedVer="false" width="24" height="24"/>
  <element name="background_5element_2" type="0" x="120" y="360" isFlipped="false" isFlippedVer="false" width="24" height="24"/>
  <element name="background_5element_2" type="0" x="144" y="360" isFlipped="false" isFlippedVer="false" width="24" height="24"/>
  <element name="background_5element_2" type="0" x="168" y="360" isFlipped="false" isFlippedVer="false" width="24" height="24"/>
  <element name="background_5element_2" type="0" x="192" y="360" isFlipped="false" isFlippedVer="false" width="24" height="24"/>
  <element name="background_5element_2" type="0" x="216" y="360" isFlipped="false" isFlippedVer="false" width="24" height="24"/>
  <element name="background_5element_2" type="0" x="240" y="360" isFlipped="false" isFlippedVer="false" width="24" height="24"/>
  <element name="background_5element_2" type="0" x="264" y="360" isFlipped="false" isFlippedVer="false" width="24" height="24"/>
  <element name="background_5element_2" type="0" x="288" y="360" isFlipped="false" isFlippedVer="false" width="24" height="24"/>
  <element name="background_5element_2" type="0" x="48" y="336" isFlipped="false" isFlippedVer="false" width="24" height="24"/>
  <element name="background_5element_2" type="0" x="48" y="312" isFlipped="false" isFlippedVer="false" width="24" height="24"/>
  <element name="background_5element_2" type="0" x="48" y="288" isFlipped="false" isFlippedVer="false" width="24" height="24"/>
  <element name="background_5element_2" type="0" x="48" y="264" isFlipped="false" isFlippedVer="false" width="24" height="24"/>
  <element name="background_5element_2" type="0" x="48" y="240" isFlipped="false" isFlippedVer="false" width="24" height="24"/>
  <element name="background_5element_2" type="0" x="48" y="216" isFlipped="false" isFlippedVer="false" width="24" height="24"/>
  <element name="background_5element_2" type="0" x="48" y="192" isFlipped="false" isFlippedVer="false" width="24" height="24"/>
  <element name="background_5element_2" type="0" x="48" y="168" isFlipped="false" isFlippedVer="false" width="24" height="24"/>
  <element name="background_5element_2" type="0" x="48" y="144" isFlipped="false" isFlippedVer="false" width="24" height="24"/>
  <element name="background_5element_2" type="0" x="48" y="120" isFlipped="false" isFlippedVer="false" width="24" height="24"/>
  <element name="background_5element_2" type="0" x="48" y="96" isFlipped="false" isFlippedVer="false" width="24" height="24"/>
  <element name="background_5element_2" type="0" x="288" y="336" isFlipped="false" isFlippedVer="false" width="24" height="24"/>
  <element name="background_5element_2" type="0" x="288" y="312" isFlipped="false" isFlippedVer="false" width="24" height="24"/>
  <element name="background_5element_2" type="0" x="288" y="288" isFlipped="false" isFlippedVer="false" width="24" height="24"/>
  <element name="background_5element_2" type="0" x="288" y="264" isFlipped="false" isFlippedVer="false" width="24" height="24"/>
  <element name="background_5element_2" type="0" x="288" y="240" isFlipped="false" isFlippedVer="false" width="24" height="24"/>
  <element name="background_5element_2" type="0" x="288" y="216" isFlipped="false" isFlippedVer="false" width="24" height="24"/>
  <element name="background_5element_2" type="0" x="288" y="192" isFlipped="false" isFlippedVer="false" width="24" height="24"/>
  <element name="background_5element_2" type="0" x="288" y="168" isFlipped="false" isFlippedVer="false" width="24" height="24"/>
  <element name="background_5element_2" type="0" x="288" y="144" isFlipped="false" isFlippedVer="false" width="24" height="24"/>
  <element name="background_5element_2" type="0" x="288" y="120" isFlipped="false" isFlippedVer="false" width="24" height="24"/>
  <element name="background_5element_2" type="0" x="288" y="96" isFlipped="false" isFlippedVer="false" width="24" height="24"/>
  <element name="background_5element_2" type="0" x="96" y="120" isFlipped="false" isFlippedVer="false" width="24" height="24"/>
  <element name="background_5element_2" type="0" x="144" y="120" isFlipped="false" isFlippedVer="false" width="24" height="24"/>
  <element name="background_5element_2" type="0" x="192" y="120" isFlipped="false" isFlippedVer="false" width="24" height="24"/>
  <element name="background_5element_2" type="0" x="240" y="120" isFlipped="false" isFlippedVer="false" width="24" height="24"/>
  <element name="background_5element_2" type="0" x="216" y="144" isFlipped="false" isFlippedVer="false" width="24" height="24"/>
  <element name="background_5element_2" type="0" x="168" y="144" isFlipped="false" isFlippedVer="false" width="24" height="24"/>
  <element name="background_5element_2" type="0" x="120" y="144" isFlipped="false" isFlippedVer="false" width="24" height="24"/>
  <element name="background_5element_2" type="0" x="96" y="168" isFlipped="false" isFlippedVer="false" width="24" height="24"/>
  <element name="background_5element_2" type="0" x="144" y="168" isFlipped="false" isFlippedVer="false" width="24" height="24"/>
  <element name="background_5element_2" type="0" x="192" y="168" isFlipped="false" isFlippedVer="false" width="24" height="24"/>
  <element name="background_5element_2" type="0" x="240" y="168" isFlipped="false" isFlippedVer="false" width="24" height="24"/>
  <element name="background_5element_2" type="0" x="216" y="192" isFlipped="false" isFlippedVer="false" width="24" height="24"/>
  <element name="background_5element_2" type="0" x="168" y="192" isFlipped="false" isFlippedVer="false" width="24" height="24"/>
  <element name="background_5element_2" type="0" x="120" y="192" isFlipped="false" isFlippedVer="false" width="24" height="24"/>
  <element name="background_5element_2" type="0" x="96" y="216" isFlipped="false" isFlippedVer="false" width="24" height="24"/>
  <element name="background_5element_2" type="0" x="144" y="216" isFlipped="false" isFlippedVer="false" width="24" height="24"/>
  <element name="background_5element_2" type="0" x="192" y="216" isFlipped="false" isFlippedVer="false" width="24" height="24"/>
  <element name="background_5element_2" type="0" x="240" y="216" isFlipped="false" isFlippedVer="false" width="24" height="24"/>
  <element name="background_5element_2" type="0" x="216" y="240" isFlipped="false" isFlippedVer="false" width="24" height="24"/>
  <element name="background_5element_2" type="0" x="168" y="240" isFlipped="false" isFlippedVer="false" width="24" height="24"/>
  <element name="background_5element_2" type="0" x="120" y="240" isFlipped="false" isFlippedVer="false" width="24" height="24"/>
  <element name="background_5element_2" type="0" x="96" y="264" isFlipped="false" isFlippedVer="false" width="24" height="24"/>
  <element name="background_5element_2" type="0" x="144" y="264" isFlipped="false" isFlippedVer="false" width="24" height="24"/>
  <element name="background_5element_2" type="0" x="192" y="264" isFlipped="false" isFlippedVer="false" width="24" height="24"/>
  <element name="background_5element_2" type="0" x="240" y="264" isFlipped="false" isFlippedVer="false" width="24" height="24"/>
  <element name="background_5element_2" type="0" x="216" y="288" isFlipped="false" isFlippedVer="false" width="24" height="24"/>
  <element name="background_5element_2" type="0" x="168" y="288" isFlipped="false" isFlippedVer="false" width="24" height="24"/>
  <element name="background_5element_2" type="0" x="120" y="288" isFlipped="false" isFlippedVer="false" width="24" height="24"/>
  <element name="background_5element_2" type="0" x="96" y="312" isFlipped="false" isFlippedVer="false" width="24" height="24"/>
  <element name="background_5element_2" type="0" x="144" y="312" isFlipped="false" isFlippedVer="false" width="24" height="24"/>
  <element name="background_5element_2" type="0" x="192" y="312" isFlipped="false" isFlippedVer="false" width="24" height="24"/>
  <element name="background_5element_2" type="0" x="240" y="312" isFlipped="false" isFlippedVer="false" width="24" height="24"/>
  <element name="background_snow_tile_4" type="0" x="48" y="360" isFlipped="false" isFlippedVer="false" width="24" height="24"/>
  <element name="background_snow_tile_2" type="0" x="72" y="336" isFlipped="false" isFlippedVer="false" width="24" height="24"/>
  <element name="background_snow_tile_2" type="0" x="72" y="336" isFlipped="true" isFlippedVer="false" width="24" height="24"/>
  <element name="background_snow_tile_4" type="0" x="96" y="360" isFlipped="true" isFlippedVer="false" width="24" height="24"/>
  <element name="background_outer_tile_1" type="0" x="0" y="0" isFlipped="false" isFlippedVer="false" width="360" height="48"/>
  <element name="background_outer_tile_2" type="0" x="24" y="48" isFlipped="false" isFlippedVer="false" width="24" height="24"/>
  <element name="background_outer_tile_3_" type="0" x="48" y="48" isFlipped="false" isFlippedVer="false" width="72" height="27"/>
  <element name="background_outer_tile_4" type="0" x="24" y="72" isFlipped="false" isFlippedVer="false" width="24" height="72"/>
  <element name="background_outer_tile_5" type="0" x="24" y="360" isFlipped="false" isFlippedVer="false" width="24" height="24"/>
  <element name="background_outer_tile_6" type="0" x="96" y="377" isFlipped="false" isFlippedVer="false" width="72" height="18"/>
  <element name="background_outer_tile_3_" type="0" x="96" y="48" isFlipped="false" isFlippedVer="false" width="72" height="27"/>
  <element name="background_outer_tile_3_" type="0" x="192" y="48" isFlipped="false" isFlippedVer="false" width="72" height="27"/>
  <element name="background_outer_tile_3_" type="0" x="240" y="48" isFlipped="false" isFlippedVer="false" width="72" height="27"/>
  <element name="background_outer_tile_4" type="0" x="24" y="144" isFlipped="false" isFlippedVer="false" width="24" height="72"/>
  <element name="background_outer_tile_4" type="0" x="24" y="240" isFlipped="false" isFlippedVer="false" width="24" height="72"/>
  <element name="background_outer_tile_4" type="0" x="24" y="288" isFlipped="false" isFlippedVer="false" width="24" height="72"/>
  <element name="background_outer_tile_6" type="0" x="48" y="377" isFlipped="false" isFlippedVer="false" width="72" height="18"/>
  <element name="background_outer_tile_6" type="0" x="192" y="377" isFlipped="false" isFlippedVer="false" width="72" height="18"/>
  <element name="background_outer_tile_6" type="0" x="240" y="377" isFlipped="false" isFlippedVer="false" width="72" height="18"/>
  <element name="background_outer_tile_2" type="0" x="336" y="48" isFlipped="true" isFlippedVer="false" width="24" height="24"/>
  <element name="background_outer_tile_4" type="0" x="336" y="72" isFlipped="true" isFlippedVer="false" width="24" height="72"/>
  <element name="background_outer_tile_5" type="0" x="336" y="360" isFlipped="true" isFlippedVer="false" width="24" height="24"/>
  <element name="background_outer_tile_4" type="0" x="336" y="144" isFlipped="true" isFlippedVer="false" width="24" height="72"/>
  <element name="background_outer_tile_4" type="0" x="336" y="240" isFlipped="true" isFlippedVer="false" width="24" height="72"/>
  <element name="background_outer_tile_4" type="0" x="336" y="288" isFlipped="true" isFlippedVer="false" width="24" height="72"/>
  <element name="background_outer_tile_1" type="0" x="0" y="384" isFlipped="false" isFlippedVer="false" width="360" height="120"/>
  <element name="background_outer_tile_1" type="0" x="336" y="48" isFlipped="false" isFlippedVer="false" width="24" height="336"/>
  <element name="background_outer_tile_1" type="0" x="0" y="48" isFlipped="false" isFlippedVer="false" width="24" height="336"/>
  <element name="background_1element_5" type="0" x="212" y="93" isFlipped="false" isFlippedVer="false" width="8" height="6"/>
  <element name="background_snow_tile_3" type="0" x="72" y="216" isFlipped="true" isFlippedVer="false" width="24" height="24"/>
  <element name="background_ice_element_7" type="0" x="96" y="72" isFlipped="false" isFlippedVer="false" width="24" height="24"/>
  <element name="background_ice_element_1" type="0" x="96" y="192" isFlipped="true" isFlippedVer="false" width="24" height="24"/>
  <element name="background_ice_element_1" type="0" x="96" y="96" isFlipped="false" isFlippedVer="false" width="24" height="24"/>
  <element name="background_ice_element_1" type="0" x="48" y="192" isFlipped="false" isFlippedVer="false" width="24" height="24"/>
  <element name="background_ice_element_4" type="0" x="48" y="168" isFlipped="false" isFlippedVer="false" width="24" height="24"/>
  <element name="background_ice_element_4" type="0" x="96" y="168" isFlipped="true" isFlippedVer="false" width="24" height="24"/>
  <element name="background_1element_5" type="0" x="152" y="345" isFlipped="false" isFlippedVer="false" width="8" height="6"/>
  <element name="background_1element_6" type="0" x="163" y="357" isFlipped="false" isFlippedVer="false" width="10" height="7"/>
  <element name="background_tile_1" type="0" x="168" y="312" isFlipped="false" isFlippedVer="false" width="24" height="24"/>
  <element name="background_tile_1" type="0" x="240" y="168" isFlipped="false" isFlippedVer="false" width="24" height="24"/>
  <element name="background_tile_1" type="0" x="96" y="168" isFlipped="false" isFlippedVer="false" width="24" height="24"/>
  <element name="background_tile_1" type="0" x="96" y="264" isFlipped="false" isFlippedVer="false" width="24" height="24"/>
  <element name="background_tile_1" type="0" x="240" y="264" isFlipped="false" isFlippedVer="false" width="24" height="24"/>
  <element name="background_tile_1" type="0" x="168" y="120" isFlipped="false" isFlippedVer="false" width="24" height="24"/>
  <element name="background_ice_element_4" type="0" x="48" y="144" isFlipped="false" isFlippedVer="false" width="24" height="24"/>
  <element name="background_ice_element_4" type="0" x="96" y="144" isFlipped="true" isFlippedVer="false" width="24" height="24"/>
  <element name="background_ice_element_7" type="0" x="96" y="120" isFlipped="true" isFlippedVer="false" width="24" height="24"/>
  <element name="background_ice_element_7" type="0" x="48" y="120" isFlipped="false" isFlippedVer="false" width="24" height="24"/>
  <element name="background_ice_element_1" type="0" x="312" y="192" isFlipped="true" isFlippedVer="false" width="24" height="24"/>
  <element name="background_ice_element_1" type="0" x="264" y="192" isFlipped="false" isFlippedVer="false" width="24" height="24"/>
  <element name="background_ice_element_4" type="0" x="264" y="168" isFlipped="false" isFlippedVer="false" width="24" height="24"/>
  <element name="background_ice_element_4" type="0" x="312" y="168" isFlipped="true" isFlippedVer="false" width="24" height="24"/>
  <element name="background_ice_element_4" type="0" x="264" y="144" isFlipped="false" isFlippedVer="false" width="24" height="24"/>
  <element name="background_ice_element_4" type="0" x="312" y="144" isFlipped="true" isFlippedVer="false" width="24" height="24"/>
  <element name="background_ice_element_7" type="0" x="312" y="120" isFlipped="true" isFlippedVer="false" width="24" height="24"/>
  <element name="background_ice_element_7" type="0" x="264" y="120" isFlipped="false" isFlippedVer="false" width="24" height="24"/>
  <element name="background_ice_element_1" type="0" x="312" y="312" isFlipped="true" isFlippedVer="false" width="24" height="24"/>
  <element name="background_ice_element_1" type="0" x="264" y="312" isFlipped="false" isFlippedVer="false" width="24" height="24"/>
  <element name="background_ice_element_4" type="0" x="264" y="288" isFlipped="false" isFlippedVer="false" width="24" height="24"/>
  <element name="background_ice_element_4" type="0" x="312" y="288" isFlipped="true" isFlippedVer="false" width="24" height="24"/>
  <element name="background_ice_element_4" type="0" x="264" y="264" isFlipped="false" isFlippedVer="false" width="24" height="24"/>
  <element name="background_ice_element_4" type="0" x="312" y="264" isFlipped="true" isFlippedVer="false" width="24" height="24"/>
  <element name="background_ice_element_7" type="0" x="312" y="240" isFlipped="true" isFlippedVer="false" width="24" height="24"/>
  <element name="background_ice_element_7" type="0" x="264" y="240" isFlipped="false" isFlippedVer="false" width="24" height="24"/>
  <element name="background_ice_element_1" type="0" x="96" y="312" isFlipped="true" isFlippedVer="false" width="24" height="24"/>
  <element name="background_ice_element_1" type="0" x="48" y="312" isFlipped="false" isFlippedVer="false" width="24" height="24"/>
  <element name="background_ice_element_4" type="0" x="48" y="288" isFlipped="false" isFlippedVer="false" width="24" height="24"/>
  <element name="background_ice_element_4" type="0" x="96" y="288" isFlipped="true" isFlippedVer="false" width="24" height="24"/>
  <element name="background_ice_element_4" type="0" x="48" y="264" isFlipped="false" isFlippedVer="false" width="24" height="24"/>
  <element name="background_ice_element_4" type="0" x="96" y="264" isFlipped="true" isFlippedVer="false" width="24" height="24"/>
  <element name="background_ice_element_7" type="0" x="96" y="240" isFlipped="true" isFlippedVer="false" width="24" height="24"/>
  <element name="background_ice_element_7" type="0" x="48" y="240" isFlipped="false" isFlippedVer="false" width="24" height="24"/>
  <element name="background_ice_element_7" type="0" x="168" y="72" isFlipped="true" isFlippedVer="false" width="24" height="24"/>
  <element name="background_ice_element_1" type="0" x="168" y="96" isFlipped="true" isFlippedVer="false" width="24" height="24"/>
  <element name="background_ice_element_2" type="0" x="120" y="96" isFlipped="false" isFlippedVer="false" width="24" height="24"/>
  <element name="background_ice_element_5" type="0" x="120" y="72" isFlipped="false" isFlippedVer="false" width="24" height="24"/>
  <element name="background_ice_element_7" type="0" x="192" y="336" isFlipped="false" isFlippedVer="false" width="24" height="24"/>
  <element name="background_ice_element_1" type="0" x="192" y="360" isFlipped="false" isFlippedVer="false" width="24" height="24"/>
  <element name="background_ice_element_7" type="0" x="264" y="336" isFlipped="true" isFlippedVer="false" width="24" height="24"/>
  <element name="background_ice_element_1" type="0" x="264" y="360" isFlipped="true" isFlippedVer="false" width="24" height="24"/>
  <element name="background_ice_element_2" type="0" x="216" y="360" isFlipped="false" isFlippedVer="false" width="24" height="24"/>
  <element name="background_ice_element_5" type="0" x="216" y="336" isFlipped="false" isFlippedVer="false" width="24" height="24"/>
  <element name="background_snow_tile_4" type="0" x="264" y="360" isFlipped="false" isFlippedVer="false" width="24" height="24"/>
  <element name="background_snow_tile_2" type="0" x="288" y="336" isFlipped="false" isFlippedVer="false" width="24" height="24"/>
  <element name="background_snow_tile_2" type="0" x="288" y="336" isFlipped="true" isFlippedVer="false" width="24" height="24"/>
  <element name="background_snow_tile_4" type="0" x="312" y="360" isFlipped="true" isFlippedVer="false" width="24" height="24"/>
  <element name="background_snow_tile_4" type="0" x="264" y="96" isFlipped="false" isFlippedVer="false" width="24" height="24"/>
  <element name="background_snow_tile_2" type="0" x="288" y="72" isFlipped="false" isFlippedVer="false" width="24" height="24"/>
  <element name="background_snow_tile_2" type="0" x="288" y="72" isFlipped="true" isFlippedVer="false" width="24" height="24"/>
  <element name="background_snow_tile_4" type="0" x="312" y="96" isFlipped="true" isFlippedVer="false" width="24" height="24"/>
  <element name="background_snow_tile_4" type="0" x="48" y="96" isFlipped="false" isFlippedVer="false" width="24" height="24"/>
  <element name="background_snow_tile_2" type="0" x="72" y="72" isFlipped="false" isFlippedVer="false" width="24" height="24"/>
  <element name="background_snow_tile_2" type="0" x="72" y="72" isFlipped="true" isFlippedVer="false" width="24" height="24"/>
  <element name="background_snow_tile_4" type="0" x="96" y="96" isFlipped="true" isFlippedVer="false" width="24" height="24"/>
  <element name="background_snow_tile_3" type="0" x="72" y="216" isFlipped="false" isFlippedVer="false" width="24" height="24"/>
  <element name="background_snow_tile_3" type="0" x="288" y="216" isFlipped="true" isFlippedVer="false" width="24" height="24"/>
  <element name="background_snow_tile_3" type="0" x="288" y="216" isFlipped="false" isFlippedVer="false" width="24" height="24"/>
  <element name="background_ice_element_9" type="0" x="208" y="368" isFlipped="false" isFlippedVer="false" width="17" height="9"/>
  <element name="background_ice_element_10" type="0" x="235" y="356" isFlipped="false" isFlippedVer="false" width="11" height="8"/>
  <element name="background_ice_element_9" type="0" x="208" y="344" isFlipped="false" isFlippedVer="false" width="17" height="9"/>
  <element name="background_ice_element_9" type="0" x="292" y="296" isFlipped="false" isFlippedVer="false" width="17" height="9"/>
  <element name="background_ice_element_10" type="0" x="271" y="284" isFlipped="false" isFlippedVer="false" width="11" height="8"/>
  <element name="background_ice_element_10" type="0" x="295" y="176" isFlipped="false" isFlippedVer="false" width="11" height="8"/>
  <element name="background_ice_element_9" type="0" x="280" y="152" isFlipped="false" isFlippedVer="false" width="17" height="9"/>
  <element name="background_ice_element_9" type="0" x="64" y="188" isFlipped="false" isFlippedVer="false" width="17" height="9"/>
  <element name="background_ice_element_10" type="0" x="55" y="140" isFlipped="false" isFlippedVer="false" width="11" height="8"/>
  <element name="background_ice_element_10" type="0" x="79" y="260" isFlipped="false" isFlippedVer="false" width="11" height="8"/>
  <element name="background_ice_element_9" type="0" x="52" y="284" isFlipped="false" isFlippedVer="false" width="17" height="9"/>
  <element name="background_5element_5" type="0" x="65" y="91" isFlipped="false" isFlippedVer="false" width="5" height="4"/>
  <element name="background_5element_3" type="0" x="57" y="86" isFlipped="false" isFlippedVer="false" width="6" height="6"/>
  <element name="background_5element_3" type="0" x="72" y="83" isFlipped="true" isFlippedVer="false" width="6" height="6"/>
  <element name="background_5element_5" type="0" x="296" y="90" isFlipped="false" isFlippedVer="false" width="5" height="4"/>
  <element name="background_5element_3" type="0" x="289" y="84" isFlipped="false" isFlippedVer="false" width="6" height="6"/>
  <element name="background_5element_3" type="0" x="73" y="228" isFlipped="false" isFlippedVer="false" width="6" height="6"/>
  <element name="background_5element_3" type="0" x="87" y="225" isFlipped="true" isFlippedVer="false" width="6" height="6"/>
  <element name="background_5element_5" type="0" x="279" y="352" isFlipped="false" isFlippedVer="false" width="5" height="4"/>
  <element name="background_5element_3" type="0" x="271" y="347" isFlipped="false" isFlippedVer="false" width="6" height="6"/>
  <element name="background_5element_3" type="0" x="286" y="344" isFlipped="true" isFlippedVer="false" width="6" height="6"/>
  <element name="background_tile_1" type="0" x="96" y="360" isFlipped="false" isFlippedVer="false" width="24" height="24"/>
  <element name="background_tile_1" type="0" x="240" y="72" isFlipped="false" isFlippedVer="false" width="24" height="24"/>
  <element name="background_tile_1" type="0" x="120" y="336" isFlipped="false" isFlippedVer="false" width="24" height="24"/>
  <element name="DoorTopScript" type="1" x="168" y="48" width="3" height="0" rotation="0"/>
  <element name="DoorRightScript" type="1" x="24" y="216" width="2" height="0" rotation="0"/>
  <element name="DoorLeftScript" type="1" x="312" y="216" width="4" height="0" rotation="0"/>
  <element name="DoorBottomScript" type="1" x="168" y="384" width="1" height="0" rotation="0"/>
  <element name="CollisionArea" type="0" x="24" y="48" width="312" height="24" rotation="0"/>
  <element name="CollisionArea" type="0" x="24" y="384" width="312" height="24" rotation="0"/>
  <element name="CollisionArea" type="0" x="24" y="72" width="24" height="312" rotation="0"/>
  <element name="CollisionArea" type="0" x="312" y="72" width="24" height="312" rotation="0"/>
  <element name="LevelEndScript" type="0" x="360" y="504" width="0" height="0" rotation="0"/>
  <element name="LevelStartScript" type="0" x="0" y="0" width="0" height="0" rotation="0"/>
  <element name="CameraOuterArea" type="0" x="24" y="24" width="312" height="432" rotation="0"/>
  <element name="CameraInnerArea" type="0" x="120" y="144" width="120" height="168" rotation="0"/>
  <element frame="1" name="isBlockScript" type="58" x="192" y="120" width="0" height="0" rotation="0" ai="0"/>
  <element frame="1" name="isBlockScript" type="58" x="192" y="312" width="0" height="0" rotation="0" ai="0"/>
  <element frame="1" name="isBlockScript" type="58" x="168" y="312" width="1" height="0" rotation="0" ai="0"/>
  <element frame="1" name="isBlockScript" type="60" x="240" y="120" width="0" height="0" rotation="0" ai="0"/>
  <element frame="1" name="isBlockScript" type="62" x="240" y="144" width="0" height="0" rotation="0" ai="0"/>
  <element frame="1" name="isBlockScript" type="63" x="240" y="192" width="0" height="0" rotation="0" ai="0"/>
  <element frame="1" name="isBlockScript" type="60" x="120" y="120" width="1" height="0" rotation="0" ai="0"/>
  <element frame="1" name="isBlockScript" type="62" x="96" y="144" width="0" height="0" rotation="0" ai="0"/>
  <element frame="1" name="isBlockScript" type="63" x="96" y="192" width="0" height="0" rotation="0" ai="0"/>
  <element frame="1" name="isBlockScript" type="68" x="72" y="144" width="0" height="0" rotation="0" ai="0"/>
  <element frame="1" name="isBlockScript" type="58" x="168" y="120" width="1" height="0" rotation="0" ai="0"/>
  <element frame="1" name="isBlockScript" type="57" x="192" y="144" width="0" height="0" rotation="0" ai="0"/>
  <element frame="1" name="isBlockScript" type="57" x="192" y="288" width="0" height="0" rotation="0" ai="0"/>
  <element frame="1" name="isBlockScript" type="57" x="144" y="144" width="0" height="0" rotation="0" ai="0"/>
  <element frame="1" name="isBlockScript" type="57" x="144" y="288" width="0" height="0" rotation="0" ai="0"/>
  <element frame="1" name="isBlockScript" type="66" x="216" y="216" width="0" height="0" rotation="0" ai="0"/>
  <element frame="1" name="isBlockScript" type="59" x="120" y="120" width="0" height="0" rotation="0" ai="0"/>
  <element frame="1" name="isBlockScript" type="59" x="216" y="120" width="0" height="0" rotation="0" ai="0"/>
  <element frame="1" name="isBlockScript" type="59" x="120" y="312" width="0" height="0" rotation="0" ai="0"/>
  <element frame="1" name="isBlockScript" type="59" x="216" y="312" width="0" height="0" rotation="0" ai="0"/>
  <element frame="1" name="isBlockScript" type="62" x="240" y="240" width="0" height="0" rotation="0" ai="0"/>
  <element frame="1" name="isBlockScript" type="62" x="96" y="240" width="0" height="0" rotation="0" ai="0"/>
  <element frame="1" name="isBlockScript" type="61" x="96" y="216" width="0" height="0" rotation="0" ai="0"/>
  <element frame="1" name="isBlockScript" type="61" x="240" y="216" width="0" height="0" rotation="0" ai="0"/>
  <element frame="1" name="isBlockScript" type="69" x="240" y="288" width="0" height="0" rotation="0" ai="0"/>
  <element frame="1" name="isBlockScript" type="69" x="120" y="288" width="1" height="0" rotation="0" ai="0"/>
  <element frame="1" name="isBlockScript" type="65" x="120" y="216" width="0" height="0" rotation="0" ai="0"/>
  <element frame="1" name="isBlockScript" type="66" x="144" y="216" width="0" height="0" rotation="0" ai="0"/>
  <element frame="1" name="isBlockScript" type="66" x="144" y="240" width="0" height="0" rotation="0" ai="0"/>
  <element frame="1" name="isBlockScript" type="66" x="192" y="216" width="0" height="0" rotation="0" ai="0"/>
  <element frame="1" name="isBlockScript" type="65" x="192" y="192" width="0" height="0" rotation="0" ai="0"/>
  <element frame="1" name="isBlockScript" type="66" x="168" y="168" width="0" height="0" rotation="0" ai="0"/>
  <element frame="1" name="isBlockScript" type="65" x="168" y="264" width="0" height="0" rotation="0" ai="0"/>
  <element frame="1" name="isBlockScript" type="68" x="240" y="336" width="0" height="0" rotation="0" ai="0"/>
  <element frame="1" name="isBlockScript" type="67" x="264" y="144" width="0" height="0" rotation="0" ai="0"/>
  <element frame="1" name="isBlockScript" type="68" x="72" y="336" width="0" height="0" rotation="0" ai="0"/>
  <element frame="1" name="IceCollisionArea" type="5" x="264" y="120" width="48" height="96" rotation="0"/>
  <element frame="1" name="IceCollisionArea" type="5" x="96" y="72" width="72" height="48" rotation="0"/>
  <element frame="1" name="IceCollisionArea" type="5" x="48" y="120" width="48" height="96" rotation="0"/>
  <element frame="1" name="IceCollisionArea" type="5" x="48" y="240" width="48" height="96" rotation="0"/>
  <element frame="1" name="IceCollisionArea" type="5" x="264" y="240" width="48" height="96" rotation="0"/>
  <element frame="1" name="IceCollisionArea" type="5" x="192" y="336" width="72" height="48" rotation="0"/>
  <element frame="1" name="HeroScript" type="0" x="168" y="216" width="0" height="0" rotation="0"/>
  <element frame="1" name="RockEnemyScript1" type="13" x="120" y="144" width="1" height="0" rotation="0" ai="0"/>
  <element frame="1" name="RockEnemyScript2" type="13" x="216" y="144" width="1" height="3" rotation="0" ai="1"/>
  <element frame="1" name="RockEnemyScript1" type="13" x="120" y="168" width="1" height="0" rotation="0" ai="0"/>
  <element frame="1" name="RockEnemyScript1" type="13" x="216" y="264" width="3" height="0" rotation="0" ai="0"/>
  <element frame="1" name="RockEnemyScript1" type="13" x="216" y="288" width="3" height="0" rotation="0" ai="0"/>
  <element frame="1" name="RockEnemyScript2" type="13" x="120" y="288" width="3" height="3" rotation="0" ai="1"/>
  <element frame="2" name="isBlockScript" type="58" x="192" y="120" width="0" height="0" rotation="0" ai="0"/>
  <element frame="2" name="isBlockScript" type="58" x="192" y="312" width="0" height="0" rotation="0" ai="0"/>
  <element frame="2" name="isBlockScript" type="58" x="168" y="312" width="1" height="0" rotation="0" ai="0"/>
  <element frame="2" name="isBlockScript" type="60" x="240" y="120" width="0" height="0" rotation="0" ai="0"/>
  <element frame="2" name="isBlockScript" type="62" x="240" y="144" width="0" height="0" rotation="0" ai="0"/>
  <element frame="2" name="isBlockScript" type="63" x="240" y="192" width="0" height="0" rotation="0" ai="0"/>
  <element frame="2" name="isBlockScript" type="60" x="120" y="120" width="1" height="0" rotation="0" ai="0"/>
  <element frame="2" name="isBlockScript" type="62" x="96" y="144" width="0" height="0" rotation="0" ai="0"/>
  <element frame="2" name="isBlockScript" type="63" x="96" y="192" width="0" height="0" rotation="0" ai="0"/>
  <element frame="2" name="isBlockScript" type="68" x="72" y="144" width="0" height="0" rotation="0" ai="0"/>
  <element frame="2" name="isBlockScript" type="58" x="168" y="120" width="1" height="0" rotation="0" ai="0"/>
  <element frame="2" name="isBlockScript" type="57" x="192" y="144" width="0" height="0" rotation="0" ai="0"/>
  <element frame="2" name="isBlockScript" type="57" x="192" y="288" width="0" height="0" rotation="0" ai="0"/>
  <element frame="2" name="isBlockScript" type="57" x="144" y="144" width="0" height="0" rotation="0" ai="0"/>
  <element frame="2" name="isBlockScript" type="57" x="144" y="288" width="0" height="0" rotation="0" ai="0"/>
  <element frame="2" name="isBlockScript" type="66" x="216" y="216" width="0" height="0" rotation="0" ai="0"/>
  <element frame="2" name="isBlockScript" type="59" x="120" y="120" width="0" height="0" rotation="0" ai="0"/>
  <element frame="2" name="isBlockScript" type="59" x="216" y="120" width="0" height="0" rotation="0" ai="0"/>
  <element frame="2" name="isBlockScript" type="59" x="120" y="312" width="0" height="0" rotation="0" ai="0"/>
  <element frame="2" name="isBlockScript" type="59" x="216" y="312" width="0" height="0" rotation="0" ai="0"/>
  <element frame="2" name="isBlockScript" type="62" x="240" y="240" width="0" height="0" rotation="0" ai="0"/>
  <element frame="2" name="isBlockScript" type="62" x="96" y="240" width="0" height="0" rotation="0" ai="0"/>
  <element frame="2" name="isBlockScript" type="61" x="96" y="216" width="0" height="0" rotation="0" ai="0"/>
  <element frame="2" name="isBlockScript" type="61" x="240" y="216" width="0" height="0" rotation="0" ai="0"/>
  <element frame="2" name="isBlockScript" type="69" x="240" y="288" width="0" height="0" rotation="0" ai="0"/>
  <element frame="2" name="isBlockScript" type="69" x="120" y="288" width="1" height="0" rotation="0" ai="0"/>
  <element frame="2" name="isBlockScript" type="65" x="120" y="216" width="0" height="0" rotation="0" ai="0"/>
  <element frame="2" name="isBlockScript" type="66" x="168" y="192" width="0" height="0" rotation="0" ai="0"/>
  <element frame="2" name="isBlockScript" type="66" x="192" y="192" width="0" height="0" rotation="0" ai="0"/>
  <element frame="2" name="isBlockScript" type="66" x="168" y="240" width="0" height="0" rotation="0" ai="0"/>
  <element frame="2" name="isBlockScript" type="65" x="144" y="240" width="0" height="0" rotation="0" ai="0"/>
  <element frame="2" name="isBlockScript" type="66" x="168" y="168" width="0" height="0" rotation="0" ai="0"/>
  <element frame="2" name="isBlockScript" type="65" x="168" y="264" width="0" height="0" rotation="0" ai="0"/>
  <element frame="2" name="isBlockScript" type="68" x="240" y="336" width="0" height="0" rotation="0" ai="0"/>
  <element frame="2" name="isBlockScript" type="67" x="264" y="144" width="0" height="0" rotation="0" ai="0"/>
  <element frame="2" name="isBlockScript" type="68" x="72" y="336" width="0" height="0" rotation="0" ai="0"/>
  <element frame="2" name="IceCollisionArea" type="5" x="264" y="120" width="48" height="96" rotation="0"/>
  <element frame="2" name="IceCollisionArea" type="5" x="96" y="72" width="72" height="48" rotation="0"/>
  <element frame="2" name="IceCollisionArea" type="5" x="48" y="120" width="48" height="96" rotation="0"/>
  <element frame="2" name="IceCollisionArea" type="5" x="48" y="240" width="48" height="96" rotation="0"/>
  <element frame="2" name="IceCollisionArea" type="5" x="264" y="240" width="48" height="96" rotation="0"/>
  <element frame="2" name="IceCollisionArea" type="5" x="192" y="336" width="72" height="48" rotation="0"/>
  <element frame="2" name="HeroScript" type="0" x="168" y="216" width="0" height="0" rotation="0"/>
  <element frame="2" name="RockEnemyScript1" type="13" x="120" y="144" width="1" height="0" rotation="0" ai="0"/>
  <element frame="2" name="RockEnemyScript2" type="13" x="216" y="144" width="1" height="3" rotation="0" ai="1"/>
  <element frame="2" name="RockEnemyScript1" type="13" x="120" y="168" width="1" height="0" rotation="0" ai="0"/>
  <element frame="2" name="RockEnemyScript1" type="13" x="216" y="264" width="3" height="0" rotation="0" ai="0"/>
  <element frame="2" name="RockEnemyScript1" type="13" x="216" y="288" width="3" height="0" rotation="0" ai="0"/>
  <element frame="2" name="RockEnemyScript2" type="13" x="120" y="288" width="3" height="3" rotation="0" ai="1"/>
  <element frame="2" name="RockEnemyScript1" type="13" x="216" y="144" width="1" height="0" rotation="0" ai="0"/>
  <element frame="2" name="RockEnemyScript1" type="13" x="120" y="288" width="3" height="0" rotation="0" ai="0"/>
  <element frame="3" name="isBlockScript" type="58" x="192" y="120" width="0" height="0" rotation="0" ai="0"/>
  <element frame="3" name="isBlockScript" type="58" x="192" y="312" width="0" height="0" rotation="0" ai="0"/>
  <element frame="3" name="isBlockScript" type="58" x="168" y="312" width="1" height="0" rotation="0" ai="0"/>
  <element frame="3" name="isBlockScript" type="60" x="240" y="120" width="0" height="0" rotation="0" ai="0"/>
  <element frame="3" name="isBlockScript" type="62" x="240" y="144" width="0" height="0" rotation="0" ai="0"/>
  <element frame="3" name="isBlockScript" type="63" x="240" y="192" width="0" height="0" rotation="0" ai="0"/>
  <element frame="3" name="isBlockScript" type="60" x="120" y="120" width="1" height="0" rotation="0" ai="0"/>
  <element frame="3" name="isBlockScript" type="62" x="96" y="144" width="0" height="0" rotation="0" ai="0"/>
  <element frame="3" name="isBlockScript" type="63" x="96" y="192" width="0" height="0" rotation="0" ai="0"/>
  <element frame="3" name="isBlockScript" type="68" x="72" y="144" width="0" height="0" rotation="0" ai="0"/>
  <element frame="3" name="isBlockScript" type="58" x="168" y="120" width="1" height="0" rotation="0" ai="0"/>
  <element frame="3" name="isBlockScript" type="57" x="192" y="144" width="0" height="0" rotation="0" ai="0"/>
  <element frame="3" name="isBlockScript" type="57" x="192" y="288" width="0" height="0" rotation="0" ai="0"/>
  <element frame="3" name="isBlockScript" type="57" x="144" y="144" width="0" height="0" rotation="0" ai="0"/>
  <element frame="3" name="isBlockScript" type="57" x="144" y="288" width="0" height="0" rotation="0" ai="0"/>
  <element frame="3" name="isBlockScript" type="66" x="216" y="216" width="0" height="0" rotation="0" ai="0"/>
  <element frame="3" name="isBlockScript" type="59" x="120" y="120" width="0" height="0" rotation="0" ai="0"/>
  <element frame="3" name="isBlockScript" type="59" x="216" y="120" width="0" height="0" rotation="0" ai="0"/>
  <element frame="3" name="isBlockScript" type="59" x="120" y="312" width="0" height="0" rotation="0" ai="0"/>
  <element frame="3" name="isBlockScript" type="59" x="216" y="312" width="0" height="0" rotation="0" ai="0"/>
  <element frame="3" name="isBlockScript" type="62" x="240" y="240" width="0" height="0" rotation="0" ai="0"/>
  <element frame="3" name="isBlockScript" type="62" x="96" y="240" width="0" height="0" rotation="0" ai="0"/>
  <element frame="3" name="isBlockScript" type="61" x="96" y="216" width="0" height="0" rotation="0" ai="0"/>
  <element frame="3" name="isBlockScript" type="61" x="240" y="216" width="0" height="0" rotation="0" ai="0"/>
  <element frame="3" name="isBlockScript" type="69" x="240" y="288" width="0" height="0" rotation="0" ai="0"/>
  <element frame="3" name="isBlockScript" type="69" x="120" y="288" width="1" height="0" rotation="0" ai="0"/>
  <element frame="3" name="isBlockScript" type="65" x="120" y="216" width="0" height="0" rotation="0" ai="0"/>
  <element frame="3" name="isBlockScript" type="66" x="168" y="192" width="0" height="0" rotation="0" ai="0"/>
  <element frame="3" name="isBlockScript" type="66" x="192" y="192" width="0" height="0" rotation="0" ai="0"/>
  <element frame="3" name="isBlockScript" type="66" x="168" y="240" width="0" height="0" rotation="0" ai="0"/>
  <element frame="3" name="isBlockScript" type="65" x="144" y="240" width="0" height="0" rotation="0" ai="0"/>
  <element frame="3" name="isBlockScript" type="66" x="168" y="120" width="0" height="0" rotation="0" ai="0"/>
  <element frame="3" name="isBlockScript" type="65" x="168" y="312" width="0" height="0" rotation="0" ai="0"/>
  <element frame="3" name="isBlockScript" type="68" x="240" y="336" width="0" height="0" rotation="0" ai="0"/>
  <element frame="3" name="isBlockScript" type="67" x="264" y="144" width="0" height="0" rotation="0" ai="0"/>
  <element frame="3" name="isBlockScript" type="68" x="72" y="336" width="0" height="0" rotation="0" ai="0"/>
  <element frame="3" name="IceCollisionArea" type="5" x="264" y="120" width="48" height="96" rotation="0"/>
  <element frame="3" name="IceCollisionArea" type="5" x="96" y="72" width="72" height="48" rotation="0"/>
  <element frame="3" name="IceCollisionArea" type="5" x="48" y="120" width="48" height="96" rotation="0"/>
  <element frame="3" name="IceCollisionArea" type="5" x="48" y="240" width="48" height="96" rotation="0"/>
  <element frame="3" name="IceCollisionArea" type="5" x="264" y="240" width="48" height="96" rotation="0"/>
  <element frame="3" name="IceCollisionArea" type="5" x="192" y="336" width="72" height="48" rotation="0"/>
  <element frame="3" name="HeroScript" type="0" x="168" y="216" width="0" height="0" rotation="0"/>
  <element frame="3" name="RockEnemyScript1" type="13" x="120" y="144" width="1" height="0" rotation="0" ai="0"/>
  <element frame="3" name="RockEnemyScript1" type="13" x="120" y="168" width="1" height="0" rotation="0" ai="0"/>
  <element frame="3" name="RockEnemyScript1" type="13" x="216" y="264" width="3" height="0" rotation="0" ai="0"/>
  <element frame="3" name="RockEnemyScript1" type="13" x="216" y="288" width="3" height="0" rotation="0" ai="0"/>
  <element frame="3" name="RockEnemyScript2" type="13" x="120" y="288" width="3" height="4" rotation="0" ai="1"/>
  <element frame="3" name="RockEnemyScript2" type="13" x="216" y="168" width="1" height="7" rotation="0" ai="1"/>
  <element frame="3" name="RockEnemyScript2" type="13" x="216" y="144" width="1" height="6" rotation="0" ai="1"/>
  <element frame="3" name="RockEnemyScript2" type="13" x="120" y="264" width="3" height="5" rotation="0" ai="1"/>
</map>